ciphit/__init__.py
ciphit/__main__.py
ciphit/__version__.py
ciphit/basemods/Ciphers/__init__.py
ciphit/basemods/Crypto/__init__.py
ciphit/basemods/Crypto/aes_128_cbc.py
ciphit/basemods/Crypto/aes_128_cbc_pass.py
ciphit/basemods/__init__.py
ciphit/cli.py
ciphit/legacy/aes.py
ciphit/legacy/ciphit.py
ciphit-0.6.2.dist-info/entry_points.txt
ciphit-0.6.2.dist-info/LICENSE
ciphit-0.6.2.dist-info/WHEEL
ciphit-0.6.2.dist-info/METADATA
ciphit-0.6.2.dist-info/RECORD
