Metadata-Version: 2.1
Name: ciphit
Version: 0.6.2
Summary: A cryptography cli-tool
Home-page: https://github.com/sgrkmr/ciphit
License: MIT
Keywords: cli,commandline,user-interface,ui,cryptography
Author: Sagar Kumar
Author-email: 57829219+sgrkmr@users.noreply.github.com
Requires-Python: >=3.7,<4.0
Classifier: License :: OSI Approved :: MIT License
Classifier: Programming Language :: Python :: 3
Classifier: Programming Language :: Python :: 3 :: Only
Classifier: Programming Language :: Python :: 3.7
Classifier: Programming Language :: Python :: 3.8
Classifier: Programming Language :: Python :: 3.9
Requires-Dist: click (>=7.1.2,<8.0.0)
Requires-Dist: click-option-group (>=0.5.1,<0.6.0)
Requires-Dist: cryptography (>=3.2,<4.0)
Requires-Dist: rich (>=8.0.0,<9.0.0)
Project-URL: Documentation, https://github.com/sgrkmr/ciphit
Project-URL: Repository, https://github.com/sgrkmr/ciphit
